llm_vertex.py
llm_vertex_fork-0.2.5.dist-info/licenses/LICENSE
llm_vertex_fork-0.2.5.dist-info/METADATA
llm_vertex_fork-0.2.5.dist-info/WHEEL
llm_vertex_fork-0.2.5.dist-info/entry_points.txt
llm_vertex_fork-0.2.5.dist-info/top_level.txt
llm_vertex_fork-0.2.5.dist-info/RECORD
